[{"address":"https://betfair-rebuild.prismic.io","color":"rgba(255,0,0,1)","fontSize":"auto","name":"PRD","position":"1","uuid":"0ac126c8-9aff-452b-b76c-941104854128"},{"address":"https://skybet.prismic.io","color":"rgba(255,0,0,1)","fontSize":"auto","name":"PRD","position":"1","uuid":"2d9b8482-ceee-4160-a417-e3ee16b12300"},{"address":"https://paddypower-sports.prismic.io","color":"rgba(255,0,0,1)","fontSize":"auto","name":"PRD","position":"1","uuid":"d19d2b6c-f0f1-4e05-9f27-c9100fc7f347"},{"address":"https://flutter-experimentation.prismic.io","color":"rgba(255,0,0,1)","fontSize":"auto","name":"PRD","position":"1","uuid":"11cbb5dc-4a45-45e7-9d76-d155871d1d90"}]